raya/__init__.py
raya/agent/__init__.py
raya/agent/service.py
raya/agent/state.py
raya/agent/utils.py
raya/agent/views.py
raya/agent/prompt/action.md
raya/agent/prompt/answer.md
raya/agent/prompt/observation.md
raya/agent/prompt/service.py
raya/agent/prompt/system.md
raya/agent/registry/service.py
raya/agent/registry/views.py
raya/agent/tools/__init__.py
raya/agent/tools/service.py
raya/agent/tools/views.py
raya/desktop/__init__.py
raya/desktop/config.py
raya/desktop/service.py
raya/desktop/views.py
raya/tree/__init__.py
raya/tree/config.py
raya/tree/service.py
raya/tree/utils.py
raya/tree/views.py
raya_agent-0.1.1.dist-info/METADATA
raya_agent-0.1.1.dist-info/WHEEL
raya_agent-0.1.1.dist-info/licenses/LICENSE
raya_agent-0.1.1.dist-info/RECORD
