Metadata-Version: 2.4
Name: raya_agent
Version: 0.1.1
Summary: A Computer-use Agent for the Windows Operating System.
Project-URL: homepage, https://github.com/iBz-04/raya
Project-URL: repository, https://github.com/iBz-04/raya
Author-email: Ibrahim Rayamah <issakaibrahimrayamah@gmail.com>
License-Expression: MIT
License-File: LICENSE
Keywords: ai,ai agent,automation,computer use agent,desktop,windows OS agent
Classifier: Development Status :: 4 - Beta
Classifier: Intended Audience :: Developers
Classifier: License :: OSI Approved :: MIT License
Classifier: Operating System :: Microsoft :: Windows
Classifier: Programming Language :: Python :: 3.13
Classifier: Topic :: Software Development :: Libraries :: Python Modules
Classifier: Topic :: Software Development :: User Interfaces
Requires-Python: >=3.13
Requires-Dist: fuzzywuzzy>=0.18.0
Requires-Dist: humancursor>=1.1.5
Requires-Dist: ipykernel>=6.29.5
Requires-Dist: langchain-community>=0.3.25
Requires-Dist: langchain-google-genai>=2.1.5
Requires-Dist: langchain-groq>=0.3.4
Requires-Dist: langchain-ollama>=0.3.3
Requires-Dist: langchain-openai>=0.3.27
Requires-Dist: langchain>=0.3.25
Requires-Dist: langgraph>=0.6.4
Requires-Dist: live-inspect==0.1.1
Requires-Dist: markdownify>=1.1.0
Requires-Dist: pillow>=11.2.1
Requires-Dist: psutil>=7.0.0
Requires-Dist: pyautogui>=0.9.54
Requires-Dist: pydantic>=2.11.7
Requires-Dist: python-levenshtein>=0.27.1
Requires-Dist: rich>=14.0.0
Requires-Dist: tabulate>=0.9.0
Requires-Dist: termcolor>=3.1.0
Requires-Dist: twine>=6.1.0
Requires-Dist: uiautomation>=2.0.28
Provides-Extra: dev
Requires-Dist: pytest>=8.4.1; extra == 'dev'
Requires-Dist: ruff>=0.12.1; extra == 'dev'
